django_credentials/__init__.py
django_credentials/apps.py
django_credentials/lib.py
django_credentials/management/__init__.py
django_credentials/management/commands/__init__.py
django_credentials/management/commands/edit_credentials.py
django_credentials/management/commands/init_credentials.py
django_credentials/tests.py
env_credentials/__init__.py
env_credentials/credentials.py
env_credentials/example.env
env_credentials-0.1.0.dist-info/LICENSE
env_credentials-0.1.0.dist-info/WHEEL
env_credentials-0.1.0.dist-info/METADATA
env_credentials-0.1.0.dist-info/RECORD
