Metadata-Version: 2.1
Name: env-credentials
Version: 0.1.0
Summary: A library to maintain and use encrypted .env files.
Home-page: https://github.com/camuthig/python-env-credentials
License: MIT
Keywords: dotenv,credentials,encrypted,settings,environment variables,env
Author: Chris Muthig
Author-email: camuthig@gmail.com
Requires-Python: >=3.6,<4.0
Classifier: License :: OSI Approved :: MIT License
Classifier: Programming Language :: Python :: 3
Classifier: Programming Language :: Python :: 3.6
Classifier: Programming Language :: Python :: 3.7
Classifier: Programming Language :: Python :: 3.8
Provides-Extra: django
Requires-Dist: cryptography (>=2.9,<3.0)
Requires-Dist: django (>=3.0,<4.0); extra == "django"
Requires-Dist: python-dotenv (>=0.13.0,<0.14.0)
Project-URL: Documentation, https://github.com/camuthig/python-env-credentials
Project-URL: Repository, https://github.com/camuthig/python-env-credentials
